{"aqi":296,"idx":8688,"attributions":[{"url":"http://unishanoi.org/","name":"UNIS - United Nations International School Of Hanoi","logo":"Vietnam-Hanoi.UNIS.png"},{"url":"https://waqi.info/","name":"World Air Quality Index Project"}],"city":{"geo":[21.0811211,105.8180306],"name":"United Nations International School of Hanoi, Vietnam (Trường Quốc tế Liên Hợp Quốc Hà Nội, Vietnam)","url":"https://aqicn.org/city/vietnam/hanoi/unis"},"dominentpol":"aqi","iaqi":{"w":{"v":1.5}},"time":{"s":"2020-01-14 10:00:00","tz":"+07:00","v":1578996000},"debug":{"sync":"2020-01-14T12:15:24+09:00"}}